{
  "errno": 0,
  "errmsg": "",
  "data": {
    "id": 129,
    "author": {
      "id": 2,
      "login": "oTUP60LImdhyvE3VpMEmYSTiefu0",
      "nicename": "请好好说话",
      "email": null,
      "status": 1,
      "liked": [
        {
          "date": "2018",
          "post_id": "1",
          "modified": "1516022724835"
        },
        {
          "date": "1987",
          "post_id": "2",
          "modified": "1516026017135"
        },
        {
          "date": "1990",
          "post_id": "7",
          "modified": "1516026344826"
        },
        {
          "date": "1988",
          "post_id": "3",
          "modified": "1516026636661"
        },
        {
          "date": "1989",
          "post_id": "4",
          "modified": "1516026655595"
        },
        {
          "date": "1988",
          "post_id": "5",
          "modified": "1516026672512"
        },
        {
          "date": "1989",
          "post_id": "6",
          "modified": "1516026686385"
        },
        {
          "date": "1995",
          "post_id": "14",
          "modified": "1516031955330"
        },
        {
          "date": "2018",
          "post_id": "20",
          "modified": "1516032193474"
        },
        {
          "date": "2011",
          "post_id": "24",
          "modified": "1516032469127"
        },
        {
          "date": "2018",
          "post_id": "26",
          "modified": "1516032553407"
        },
        {
          "date": "2018",
          "post_id": "28",
          "modified": "1516032634649"
        },
        {
          "date": "2018",
          "post_id": "41",
          "modified": "1516058291839"
        },
        {
          "date": "2018",
          "post_id": "43",
          "modified": "1516060536166"
        },
        {
          "date": "2018",
          "post_id": "45",
          "modified": "1516060632319"
        },
        {
          "date": "2018",
          "post_id": "47",
          "modified": "1516060780676"
        },
        {
          "date": "2018",
          "post_id": "49",
          "modified": "1516060877758"
        },
        {
          "date": "2018",
          "post_id": "51",
          "modified": "1516062579593"
        },
        {
          "date": "2018",
          "post_id": "53",
          "modified": "1516062658393"
        },
        {
          "date": "2018",
          "post_id": "55",
          "modified": "1516062704252"
        },
        {
          "date": "2018",
          "post_id": "57",
          "modified": "1516062791045"
        },
        {
          "date": "2016",
          "post_id": "59",
          "modified": "1516062909194"
        },
        {
          "date": "2018",
          "post_id": "36",
          "modified": "1516063684609"
        },
        {
          "date": "2018",
          "post_id": "61",
          "modified": "1516069811087"
        },
        {
          "date": "2000",
          "post_id": "33",
          "modified": "1516070219914"
        },
        {
          "date": "1991",
          "post_id": "30",
          "modified": "1516070237551"
        },
        {
          "date": "2013",
          "post_id": "63",
          "modified": "1516070611522"
        },
        {
          "date": "2018",
          "post_id": "69",
          "modified": "1516077259709"
        },
        {
          "date": "2018",
          "post_id": "72",
          "modified": "1516077699143"
        },
        {
          "date": "2018",
          "post_id": "66",
          "modified": "1516078210569"
        },
        {
          "date": "2018",
          "post_id": "77",
          "modified": "1516115236647"
        },
        {
          "date": "1991",
          "post_id": "75",
          "modified": "1516115487108"
        },
        {
          "date": "2018",
          "post_id": "92",
          "modified": "1516142111561"
        },
        {
          "date": "1999",
          "post_id": "89",
          "modified": "1516142590267"
        },
        {
          "date": "2012",
          "post_id": "95",
          "modified": "1516159066543"
        },
        {
          "date": "2013",
          "post_id": "98",
          "modified": "1516161114317"
        },
        {
          "date": "2013",
          "post_id": "100",
          "modified": "1516161151358"
        },
        {
          "date": "2013",
          "post_id": "102",
          "modified": "1516161258665"
        },
        {
          "date": "2013",
          "post_id": "105",
          "modified": "1516161326108"
        },
        {
          "date": "2014",
          "post_id": "107",
          "modified": "1516161363512"
        },
        {
          "date": "2015",
          "post_id": "109",
          "modified": "1516161476746"
        },
        {
          "date": "2015",
          "post_id": "111",
          "modified": "1516161507978"
        },
        {
          "date": "2015",
          "post_id": "113",
          "modified": "1516161538761"
        },
        {
          "date": "2015",
          "post_id": "115",
          "modified": "1516161564604"
        },
        {
          "date": "2016",
          "post_id": "117",
          "modified": "1516161594407"
        },
        {
          "date": "2016",
          "post_id": "119",
          "modified": "1516161768081"
        },
        {
          "date": "2016",
          "post_id": "121",
          "modified": "1516161844594"
        },
        {
          "date": "2017",
          "post_id": "123",
          "modified": "1516161877654"
        },
        {
          "date": "2017",
          "post_id": "125",
          "modified": "1516162020231"
        },
        {
          "date": "2014",
          "post_id": "127",
          "modified": "1516162167952"
        },
        {
          "date": "2016",
          "post_id": "129",
          "modified": "1516162286925"
        }
      ],
      "avatar": "https://wx.qlogo.cn/mmopen/vi_32/DYAIOgq83eoVGurHNyn6Oo5XXVm4SIEL2PP9doPF8UQT9vwkZ7Rr4adalurwXnAuO9F4VFlY3nIdWNmhrG8esA/0"
    },
    "status": "auto-draft",
    "type": "post_format",
    "title": "手擀面",
    "name": "shou-gan-mian",
    "content": null,
    "sort": 0,
    "excerpt": null,
    "date": 1516162286915,
    "modified": 1516162334215,
    "parent": 0,
    "meta": {
      "_liked": [
        {
          "id": "2",
          "ip": "3745554300",
          "date": "2016",
          "modified": "1516162286922"
        }
      ],
      "_thumbnail_id": 130
    },
    "url": "",
    "featured_image": "https://data.caixie.top/upload_892cc59f2ab3067216e7cc098895be83.jpg",
    "categories": [
      {
        "term_id": 1,
        "name": "最爱",
        "slug": "loves",
        "term_taxonomy_id": 1,
        "taxonomy": "category",
        "description": "最爱的",
        "parent": 0,
        "count": 0,
        "meta": {}
      }
    ],
    "children": [],
    "chnum": 0,
    "tags": [],
    "like_date": "2016",
    "like_count": 1,
    "i_like": true,
    "likes": [
      {
        "id": 2,
        "user_login": "oTUP60LImdhyvE3VpMEmYSTiefu0",
        "user_pass": null,
        "user_nicename": "请好好说话",
        "user_email": null,
        "user_url": null,
        "user_registered": 1516021523364,
        "user_activation_key": null,
        "user_status": 1,
        "display_name": null,
        "spam": 0,
        "deleted": 0,
        "user_phone": null,
        "role": "subscriber",
        "type": "wechat",
        "avatar": "https://wx.qlogo.cn/mmopen/vi_32/DYAIOgq83eoVGurHNyn6Oo5XXVm4SIEL2PP9doPF8UQT9vwkZ7Rr4adalurwXnAuO9F4VFlY3nIdWNmhrG8esA/0"
      }
    ]
  }
}